grouped_timeserie_cv/__init__.py
grouped_timeserie_cv/data_preprocessor.py
grouped_timeserie_cv/grouped_timeserie_cv.py
grouped_timeserie_cv/hyperparameter_tuning.py
grouped_timeserie_cv/learning_curve_calculator.py
grouped_timeserie_cv/model_evaluator.py
grouped_timeserie_cv/plotter.py
grouped_timeserie_cv/data_class/__init__.py
grouped_timeserie_cv/data_class/cross_validation_result.py
grouped_timeserie_cv-0.1.1.dist-info/licenses/LICENSE.md
grouped_timeserie_cv-0.1.1.dist-info/METADATA
grouped_timeserie_cv-0.1.1.dist-info/WHEEL
grouped_timeserie_cv-0.1.1.dist-info/top_level.txt
grouped_timeserie_cv-0.1.1.dist-info/RECORD
