Metadata-Version: 2.4
Name: grouped_timeserie_cv
Version: 0.1.1
Summary: A machine learning library based on sklearn that supports grouped time series cross-validation
Home-page: https://github.com/zenta-ab/grouped_timeserie_cv
Author: Zenta AB
Author-email: admin@zenta.se
Classifier: Programming Language :: Python :: 3
Classifier: License :: OSI Approved :: MIT License
Classifier: Operating System :: OS Independent
Requires-Python: >=3.6
License-File: LICENSE.md
Requires-Dist: plotly
Requires-Dist: pandas
Requires-Dist: scikit-learn
Requires-Dist: matplotlib
Dynamic: author
Dynamic: author-email
Dynamic: classifier
Dynamic: description
Dynamic: description-content-type
Dynamic: home-page
Dynamic: license-file
Dynamic: requires-dist
Dynamic: requires-python
Dynamic: summary
